django_golem-0.90b0.dist-info/DESCRIPTION.rst
django_golem-0.90b0.dist-info/METADATA
django_golem-0.90b0.dist-info/RECORD
django_golem-0.90b0.dist-info/WHEEL
django_golem-0.90b0.dist-info/entry_points.txt
django_golem-0.90b0.dist-info/metadata.json
django_golem-0.90b0.dist-info/top_level.txt
golem/__init__.py
golem/__main__.py
golem/apps.py
golem/models.py
golem/tasks.py
golem/tests.py
golem/urls.py
golem/views.py
golem/bootstrap/__init__.py
golem/core/__init__.py
golem/core/admin.py
golem/core/chat_session.py
golem/core/context.py
golem/core/dialog_manager.py
golem/core/flow.py
golem/core/logger.py
golem/core/message_logger.py
golem/core/message_parser.py
golem/core/persistence.py
golem/core/serialize.py
golem/core/templates.py
golem/core/tests.py
golem/core/interfaces/__init__.py
golem/core/interfaces/all.py
golem/core/interfaces/facebook.py
golem/core/interfaces/google.py
golem/core/interfaces/microsoft.py
golem/core/interfaces/telegram.py
golem/core/interfaces/test.py
golem/core/logging/__init__.py
golem/core/logging/abs_logger.py
golem/core/logging/chatbase.py
golem/core/logging/elastic.py
golem/core/parsing/__init__.py
golem/core/parsing/date_utils.py
golem/core/parsing/duckling_extractor.py
golem/core/parsing/entity_extractor.py
golem/core/parsing/golem_extractor.py
golem/core/parsing/wit_extractor.py
golem/core/responses/__init__.py
golem/core/responses/buttons.py
golem/core/responses/quick_reply.py
golem/core/responses/responses.py
golem/core/responses/settings.py
golem/core/responses/templates.py
golem/management/__init__.py
golem/management/commands/__init__.py
golem/management/commands/nlp_parse.py
golem/management/commands/test_nlp.py
golem/management/commands/train_nlp.py
golem/migrations/0001_initial.py
golem/migrations/0002_chat.py
golem/migrations/0003_auto_20180207_2331.py
golem/migrations/0004_webmessagedata.py
golem/migrations/__init__.py
golem/nlu/__init__.py
golem/nlu/cleanup.py
golem/nlu/data_model.py
golem/nlu/duckling.py
golem/nlu/fuzzy.py
golem/nlu/geneea.py
golem/nlu/glove.py
golem/nlu/keywords.py
golem/nlu/predict.py
golem/nlu/train.py
golem/nlu/utils.py
golem/nlu/gui/__init__.py
golem/nlu/gui/forms.py
golem/nlu/gui/views.py
golem/nlu/nn/__init__.py
