Metadata-Version: 2.0
Name: django-golem
Version: 0.90b0
Summary: Framework for creating stateful chatbots on Django.
Home-page: https://github.com/prihoda/golem
Author: David Příhoda, Jakub Drdák, Matúš Žilinec
Author-email: david.prihoda@gmail.com
License: Apache Software License
Platform: UNKNOWN
Classifier: Environment :: Web Environment
Classifier: Framework :: Django
Classifier: Intended Audience :: Developers
Classifier: License :: OSI Approved :: Apache Software License
Classifier: Operating System :: OS Independent
Classifier: Programming Language :: Python
Classifier: Programming Language :: Python :: 3
Classifier: Programming Language :: Python :: 3.4
Classifier: Programming Language :: Python :: 3.5
Classifier: Programming Language :: Python :: 3.6
Classifier: Topic :: Internet :: WWW/HTTP
Classifier: Topic :: Internet :: WWW/HTTP :: Dynamic Content
Requires-Dist: django
Requires-Dist: networkx
Requires-Dist: requests
Requires-Dist: six
Requires-Dist: sqlparse
Requires-Dist: wit (==4.3.0)
Requires-Dist: wheel
Requires-Dist: redis
Requires-Dist: pytz
Requires-Dist: unidecode
Requires-Dist: emoji
Requires-Dist: elasticsearch
Requires-Dist: celery
Requires-Dist: python-dateutil
